densitty/__init__.py
densitty/ansi.py
densitty/ascii_art.py
densitty/axis.py
densitty/binning.py
densitty/detect.py
densitty/lineart.py
densitty/plot.py
densitty/smoothing.py
densitty/truecolor.py
densitty/util.py
densitty/util.pyi
densitty-0.9.0.dist-info/licenses/LICENSE
densitty-0.9.0.dist-info/METADATA
densitty-0.9.0.dist-info/WHEEL
densitty-0.9.0.dist-info/top_level.txt
densitty-0.9.0.dist-info/RECORD
