Metadata-Version: 2.4
Name: densitty
Version: 0.9.0
Summary: densitty - create textual 2-D density plots, heatmaps, and 2-D histograms in Python
Author: Bill Tompkins
License-Expression: MIT
Project-URL: Homepage, https://github.com/BillTompkins/densitty
Keywords: densitty,ascii,ascii-art,plotting,terminal,Python
Classifier: Development Status :: 4 - Beta
Classifier: Environment :: Console
Classifier: Operating System :: OS Independent
Classifier: Intended Audience :: Developers
Classifier: Programming Language :: Python :: 3 :: Only
Classifier: Programming Language :: Python :: 3.10
Classifier: Programming Language :: Python :: 3.11
Classifier: Programming Language :: Python :: 3.12
Classifier: Programming Language :: Python :: 3.13
Classifier: Programming Language :: Python :: 3.14
Classifier: Programming Language :: Python :: Free Threading :: 3 - Stable
Classifier: Topic :: Software Development :: Libraries :: Python Modules
Requires-Python: >=3.10
License-File: LICENSE
Dynamic: license-file
